adtrees/__init__.py
adtrees/adnode.py
adtrees/adtparser.py
adtrees/adtree.py
adtrees/attribute_domain.py
adtrees/basic_assignment.py
adtrees/default_domains.py
adtrees/linear_programming.py
adtrees/lp_solve.py
adtrees/optimizers.py
adtrees/osead.py
adtrees/pareto_domain.py
adtrees/utils.py
adtrees-0.0.6.dist-info/METADATA
adtrees-0.0.6.dist-info/RECORD
adtrees-0.0.6.dist-info/WHEEL
adtrees-0.0.6.dist-info/top_level.txt
