Metadata-Version: 2.1
Name: adtrees
Version: 0.0.6
Summary: Implementation of attack(-defense) trees.
Home-page: https://github.com/wwidel/adtrees/
Author: Wojciech Widel
Author-email: wwidel@irisa.fr
License: UNKNOWN
Platform: UNKNOWN
Classifier: Programming Language :: Python :: 3
Classifier: License :: OSI Approved :: GNU General Public License v3 (GPLv3)
Classifier: Operating System :: OS Independent
Provides-Extra: testing
Requires-Dist: numpy (==1.15.2)
Requires-Dist: scipy (==1.1.0)
Provides-Extra: testing
Requires-Dist: pytest; extra == 'testing'
